MANIFEST.in
requirements.txt
setup.py
libbmc/__init__.py
libbmc/bibtex.py
libbmc/doi.py
libbmc/fetcher.py
libbmc/isbn.py
libbmc/tools.py
libbmc.egg-info/PKG-INFO
libbmc.egg-info/SOURCES.txt
libbmc.egg-info/dependency_links.txt
libbmc.egg-info/requires.txt
libbmc.egg-info/top_level.txt
libbmc/citations/__init__.py
libbmc/citations/bbl.py
libbmc/citations/bibtex.py
libbmc/citations/pdf.py
libbmc/citations/plaintext.py
libbmc/papers/__init__.py
libbmc/papers/identifiers.py
libbmc/papers/tearpages.py
libbmc/repositories/__init__.py
libbmc/repositories/arxiv.py
libbmc/repositories/hal.py