Metadata-Version: 1.0
Name: libbmc
Version: 0.2
Summary: A python library to deal with scientific papers.
Home-page: https://github.com/Phyks/libbmc/
Author: Phyks (Lucas Verney)
Author-email: phyks@phyks.me
License: MIT License
Platform: UNKNOWN
